terraref/__init__.py
terraref/terrautils/__init__.py
terraref/terrautils/betydb.py
terraref/terrautils/extractors.py
terraref/terrautils/formats.py
terraref/terrautils/gdal.py
terraref/terrautils/geostreams.py
terraref/terrautils/influx.py
terraref/terrautils/lemnatec.py
terraref/terrautils/metadata.py
terraref/terrautils/products.py
terraref/terrautils/sensors.py
terraref/terrautils/spatial.py
terrautils-1.1.0.dist-info/DESCRIPTION.rst
terrautils-1.1.0.dist-info/METADATA
terrautils-1.1.0.dist-info/RECORD
terrautils-1.1.0.dist-info/WHEEL
terrautils-1.1.0.dist-info/metadata.json
terrautils-1.1.0.dist-info/top_level.txt
