Metadata-Version: 2.0
Name: terrautils
Version: 1.1.0
Summary: TERRA-REF utility library
Home-page: https://terraref.org
Author: Max Burnette
Author-email: mburnet2@illinois.edu
License: BSD
Project-URL: Source, https://github.com/terraref/terrautils
Project-URL: Tracker, https://github.com/terraref/terrautils/issues
Keywords: terraref,clowder,field crop
Platform: UNKNOWN
Classifier: Development Status :: 4 - Beta
Classifier: Intended Audience :: Science/Research
Classifier: Topic :: Scientific/Engineering :: Bio-Informatics
Classifier: License :: OSI Approved :: BSD License
Classifier: Programming Language :: Python :: 2.7
Requires-Dist: cfunits
Requires-Dist: influxdb
Requires-Dist: matplotlib
Requires-Dist: netCDF4
Requires-Dist: numpy
Requires-Dist: Pillow
Requires-Dist: python-dateutil
Requires-Dist: scipy
Requires-Dist: utm
Requires-Dist: python-logstash
Requires-Dist: pyclowder (<3,>=2)
